{
  "default": {
    "demo_name": "Default Demo",
    "theme_slug": "wp-diary",
    "theme_description": "A pure blogger free WordPress Theme.",
    "xml_file": "https://raw.githubusercontent.com/mysterythemes/themes-demo-pack/master/wp-diary/default/wp-diary.xml",
    "theme_settings": "https://raw.githubusercontent.com/mysterythemes/themes-demo-pack/master/wp-diary/default/wp-diary-export.dat",
    "widgets_file": "https://raw.githubusercontent.com/mysterythemes/themes-demo-pack/master/wp-diary/default/wp-diary-widgets.wie",
    "preview_screen": "https://raw.githubusercontent.com/mysterythemes/themes-demo-pack/master/wp-diary/default/screenshot.jpg",
    "preview_url": "https://demo.mysterythemes.com/wp-diary/",
    "is_shop": "0",
    "theme_type": [
      "free",
      "blog",
      "portfolio"
    ],
    "home_title": "",
    "blog_title": "",
    "menus_locations": {
      "primary_menu": "front menu",
      "footer_menu": "front menu"
    },
    "required_plugins": {
      "free-plugins": [
        {
          "plugin_name": "Contact Form 7",
          "plugin_slug": "contact-form-7",
          "install_setup": "contact-form-7/wp-contact-form-7.php"
        }
      ]
    }
  }
}